[ {
  "id" : "ddc39863-dc9f-a4e4-18dd-c0f6c889ffcb",
  "name" : "title",
  "label" : "Title",
  "required" : false,
  "locked" : false,
  "validation_regex" : "",
  "allow_new_line" : false,
  "show_emoji_picker" : false,
  "type" : "text",
  "display_width" : null,
  "default" : "Leading enterprise organizations run finance on AppZen"
}, {
  "id" : "c141dfee-46e1-f57e-1a7b-83d974c40c82",
  "name" : "select_post_type",
  "label" : "Select Post Type",
  "required" : false,
  "locked" : false,
  "display" : "select",
  "choices" : [ [ "recent", "Recent" ], [ "pbt", "Post By Title" ] ],
  "multiple" : false,
  "reordering_enabled" : true,
  "preset" : null,
  "type" : "choice",
  "display_width" : null,
  "default" : "recent"
}, {
  "id" : "fb7b8c92-586f-469e-e519-ef52d9359cdc",
  "name" : "select_hubdb_table",
  "label" : "Select HubDB Table",
  "required" : false,
  "locked" : false,
  "visibility" : {
    "controlling_field" : null,
    "controlling_field_path" : "select_post_type",
    "controlling_value_regex" : "recent",
    "property" : null,
    "operator" : "EQUAL",
    "access" : null
  },
  "type" : "hubdbtable",
  "display_width" : null,
  "default" : 103427390
}, {
  "id" : "61f54183-b4ae-c1e2-79ca-04b6a9624227",
  "name" : "post_by_title",
  "label" : "Posts By Title",
  "required" : false,
  "locked" : false,
  "occurrence" : {
    "min" : 4,
    "max" : null,
    "sorting_label_field" : "f4e88038-7385-d46b-bfb2-eae2de1bbcea",
    "default" : 4
  },
  "visibility" : {
    "controlling_field" : null,
    "controlling_field_path" : "select_post_type",
    "controlling_value_regex" : "pbt",
    "property" : null,
    "operator" : "EQUAL",
    "access" : null
  },
  "children" : [ {
    "id" : "f4e88038-7385-d46b-bfb2-eae2de1bbcea",
    "name" : "select_row",
    "label" : "Select Row",
    "required" : false,
    "locked" : false,
    "table_name_or_id" : "103427390",
    "display_columns" : [ "name" ],
    "type" : "hubdbrow",
    "display_width" : null,
    "default" : {
      "id" : 183455388193
    }
  } ],
  "tab" : "CONTENT",
  "expanded" : false,
  "group_occurrence_meta" : null,
  "type" : "group",
  "display_width" : null,
  "default" : [ {
    "select_row" : {
      "id" : 183455388193
    }
  }, {
    "select_row" : {
      "id" : 183455388193
    }
  }, {
    "select_row" : {
      "id" : 183455388193
    }
  }, {
    "select_row" : {
      "id" : 183455388193
    }
  } ]
}, {
  "id" : "26108238-a8bd-d3f2-a823-f12a1d6fc8b6",
  "name" : "enable_card_button",
  "label" : "Enable Card Button",
  "required" : false,
  "locked" : false,
  "visibility" : {
    "controlling_field" : null,
    "controlling_field_path" : "select_post_type",
    "controlling_value_regex" : "pbt|recent",
    "property" : null,
    "operator" : "MATCHES_REGEX",
    "access" : null
  },
  "display" : "checkbox",
  "type" : "boolean",
  "display_width" : null,
  "default" : false
}, {
  "id" : "module_overrides",
  "name" : "module_overrides",
  "label" : "Module Overrides",
  "required" : false,
  "locked" : false,
  "children" : [ {
    "id" : "enable_overrides",
    "name" : "enable_overrides",
    "label" : "Enable Overrides",
    "help_text" : "Toggle to override section ID and vertical margin. ",
    "required" : false,
    "locked" : false,
    "display" : "checkbox",
    "type" : "boolean",
    "display_width" : null,
    "default" : true
  }, {
    "id" : "module_overrides.section_id",
    "name" : "section_id",
    "label" : "Section ID",
    "help_text" : "The value you type here will be the anchor link for this section. Should be all lowercase and include dashes instead of spaces. This should be a unique value per module.",
    "required" : false,
    "locked" : false,
    "validation_regex" : "",
    "visibility" : {
      "controlling_field" : "enable_overrides",
      "controlling_field_path" : null,
      "controlling_value_regex" : "true",
      "property" : null,
      "operator" : "EQUAL",
      "access" : null
    },
    "allow_new_line" : false,
    "show_emoji_picker" : false,
    "type" : "text",
    "display_width" : null
  }, {
    "id" : "module_overrides.top_margin",
    "name" : "top_margin",
    "label" : "Top Margin",
    "required" : false,
    "locked" : false,
    "visibility" : {
      "controlling_field" : "enable_overrides",
      "controlling_field_path" : null,
      "controlling_value_regex" : "true",
      "property" : null,
      "operator" : "EQUAL",
      "access" : null
    },
    "display" : "select",
    "choices" : [ [ "top-margin-default", "Default" ], [ "top-margin-none", "None" ], [ "top-margin-small", "Small" ], [ "top-margin-medium", "Medium" ], [ "top-margin-large", "Large" ], [ "top-margin-custom", "Custom" ] ],
    "multiple" : false,
    "reordering_enabled" : true,
    "preset" : null,
    "type" : "choice",
    "display_width" : null,
    "default" : "top-margin-default"
  }, {
    "id" : "custom_top_margin",
    "name" : "custom_top_margin",
    "label" : "Custom Top Margin",
    "required" : false,
    "locked" : false,
    "visibility" : {
      "controlling_field" : "module_overrides.top_margin",
      "controlling_field_path" : null,
      "controlling_value_regex" : "top-margin-custom",
      "property" : null,
      "operator" : "EQUAL",
      "access" : null
    },
    "display" : "text",
    "step" : 1,
    "type" : "number",
    "display_width" : null,
    "default" : 100
  }, {
    "id" : "custom_top_margin_mobile",
    "name" : "custom_top_margin_mobile",
    "label" : "Custom Top Margin Mobile",
    "required" : false,
    "locked" : false,
    "visibility" : {
      "controlling_field" : "module_overrides.top_margin",
      "controlling_field_path" : null,
      "controlling_value_regex" : "top-margin-custom",
      "property" : null,
      "operator" : "EQUAL",
      "access" : null
    },
    "display" : "text",
    "step" : 1,
    "type" : "number",
    "display_width" : null,
    "default" : 50
  }, {
    "id" : "module_overrides.bottom_margin",
    "name" : "bottom_margin",
    "label" : "Bottom Margin",
    "required" : false,
    "locked" : false,
    "visibility" : {
      "controlling_field" : "enable_overrides",
      "controlling_field_path" : null,
      "controlling_value_regex" : "true",
      "property" : null,
      "operator" : "EQUAL",
      "access" : null
    },
    "display" : "select",
    "choices" : [ [ "bottom-margin-default", "Default" ], [ "bottom-margin-none", "None" ], [ "bottom-margin-small", "Small" ], [ "bottom-margin-medium", "Medium" ], [ "bottom-margin-large", "Large" ], [ "bottom-margin-custom", "Custom" ] ],
    "multiple" : false,
    "reordering_enabled" : true,
    "preset" : null,
    "type" : "choice",
    "display_width" : null,
    "default" : "bottom-margin-default"
  }, {
    "id" : "custom_bottom_margin",
    "name" : "custom_bottom_margin",
    "label" : "Custom Bottom Margin",
    "required" : false,
    "locked" : false,
    "visibility" : {
      "controlling_field" : "module_overrides.bottom_margin",
      "controlling_field_path" : null,
      "controlling_value_regex" : "bottom-margin-custom",
      "property" : null,
      "operator" : "EQUAL",
      "access" : null
    },
    "display" : "text",
    "step" : 1,
    "type" : "number",
    "display_width" : null,
    "default" : 100
  }, {
    "id" : "custom_bottom_margin_mobile",
    "name" : "custom_bottom_margin_mobile",
    "label" : "Custom Bottom Margin Mobile",
    "required" : false,
    "locked" : false,
    "visibility" : {
      "controlling_field" : "module_overrides.bottom_margin",
      "controlling_field_path" : null,
      "controlling_value_regex" : "bottom-margin-custom",
      "property" : null,
      "operator" : "EQUAL",
      "access" : null
    },
    "display" : "text",
    "step" : 1,
    "type" : "number",
    "display_width" : null,
    "default" : 50
  }, {
    "id" : "module_overrides.top_padding",
    "name" : "top_padding",
    "label" : "Top Padding",
    "required" : false,
    "locked" : false,
    "visibility" : {
      "controlling_field" : "enable_overrides",
      "controlling_field_path" : null,
      "controlling_value_regex" : "true",
      "property" : null,
      "operator" : "EQUAL",
      "access" : null
    },
    "display" : "select",
    "choices" : [ [ "top-padding-default", "Default" ], [ "top-padding-none", "None" ], [ "top-padding-small", "Small" ], [ "top-padding-medium", "Medium" ], [ "top-padding-large", "Large" ], [ "top-padding-custom", "Custom" ] ],
    "multiple" : false,
    "reordering_enabled" : true,
    "preset" : null,
    "type" : "choice",
    "display_width" : null,
    "default" : "top-padding-default"
  }, {
    "id" : "custom_top_padding",
    "name" : "custom_top_padding",
    "label" : "Custom Top Padding",
    "required" : false,
    "locked" : false,
    "visibility" : {
      "controlling_field" : "module_overrides.top_padding",
      "controlling_field_path" : null,
      "controlling_value_regex" : "top-padding-custom",
      "property" : null,
      "operator" : "EQUAL",
      "access" : null
    },
    "display" : "text",
    "step" : 1,
    "type" : "number",
    "display_width" : null,
    "default" : 100
  }, {
    "id" : "custom_top_padding_mobile",
    "name" : "custom_top_padding_mobile",
    "label" : "Custom Top Padding Mobile",
    "required" : false,
    "locked" : false,
    "visibility" : {
      "controlling_field" : "module_overrides.top_padding",
      "controlling_field_path" : null,
      "controlling_value_regex" : "top-padding-custom",
      "property" : null,
      "operator" : "EQUAL",
      "access" : null
    },
    "display" : "text",
    "step" : 1,
    "type" : "number",
    "display_width" : null,
    "default" : 50
  }, {
    "id" : "module_overrides.bottom_padding",
    "name" : "bottom_padding",
    "label" : "Bottom Padding",
    "required" : false,
    "locked" : false,
    "visibility" : {
      "controlling_field" : "enable_overrides",
      "controlling_field_path" : null,
      "controlling_value_regex" : "true",
      "property" : null,
      "operator" : "EQUAL",
      "access" : null
    },
    "display" : "select",
    "choices" : [ [ "bottom-padding-default", "Default" ], [ "bottom-padding-none", "None" ], [ "bottom-padding-small", "Small" ], [ "bottom-padding-medium", "Medium" ], [ "bottom-padding-large", "Large" ], [ "bottom-padding-custom", "Custom" ] ],
    "multiple" : false,
    "reordering_enabled" : true,
    "preset" : null,
    "type" : "choice",
    "display_width" : null,
    "default" : "bottom-padding-default"
  }, {
    "id" : "custom_bottom_padding",
    "name" : "custom_bottom_padding",
    "label" : "Custom Bottom Padding",
    "required" : false,
    "locked" : false,
    "visibility" : {
      "controlling_field" : "module_overrides.bottom_padding",
      "controlling_field_path" : null,
      "controlling_value_regex" : "bottom-padding-custom",
      "property" : null,
      "operator" : "EQUAL",
      "access" : null
    },
    "display" : "text",
    "step" : 1,
    "type" : "number",
    "display_width" : null,
    "default" : 100
  }, {
    "id" : "custom_bottom_padding_mobile",
    "name" : "custom_bottom_padding_mobile",
    "label" : "Custom Bottom Padding Mobile",
    "required" : false,
    "locked" : false,
    "visibility" : {
      "controlling_field" : "module_overrides.bottom_padding",
      "controlling_field_path" : null,
      "controlling_value_regex" : "bottom-padding-custom",
      "property" : null,
      "operator" : "EQUAL",
      "access" : null
    },
    "display" : "text",
    "step" : 1,
    "type" : "number",
    "display_width" : null,
    "default" : 50
  }, {
    "id" : "3acc8068-a3e9-1ee0-60c7-9dbf953422a4",
    "name" : "background_settings",
    "label" : "Background Settings",
    "required" : false,
    "locked" : false,
    "visibility" : {
      "controlling_field" : null,
      "controlling_field_path" : "module_overrides.enable_overrides",
      "controlling_value_regex" : "true",
      "property" : null,
      "operator" : "EQUAL",
      "access" : null
    },
    "children" : [ {
      "id" : "8c61112d-4e81-6eb2-c3da-f21a5bc9642e",
      "name" : "background_type",
      "label" : "Background Type",
      "required" : false,
      "locked" : false,
      "display" : "select",
      "choices" : [ [ "image", "Image" ], [ "color", "Color" ] ],
      "multiple" : false,
      "reordering_enabled" : true,
      "preset" : null,
      "type" : "choice",
      "display_width" : null,
      "default" : "color"
    }, {
      "id" : "0b377766-45a1-d996-07a1-ed7902a91581",
      "name" : "select_background_color_type",
      "label" : "Select Background Color",
      "required" : false,
      "locked" : false,
      "visibility" : {
        "controlling_field" : null,
        "controlling_field_path" : "module_overrides.background_settings.background_type",
        "controlling_value_regex" : "color",
        "property" : null,
        "operator" : "EQUAL",
        "access" : null
      },
      "display" : "select",
      "choices" : [ [ "brown", "Cacao" ], [ "lightGreybg", "Ivory Soft" ], [ "light_grey", "Ivory" ], [ "grey", "Bone" ], [ "yellow", "Cassava" ], [ "light_pink", "Coral" ], [ "white_bg", "White" ], [ "custom", "Custom" ] ],
      "multiple" : false,
      "reordering_enabled" : true,
      "preset" : null,
      "type" : "choice",
      "display_width" : null,
      "default" : "brown"
    }, {
      "id" : "6c8bfd0e-1629-1268-e01c-17b4047ecfce",
      "name" : "background_color",
      "label" : "Background Color",
      "help_text" : "If a module has formal settings for a background color they will take priority over this value.",
      "inline_help_text" : "",
      "required" : false,
      "locked" : false,
      "visibility" : {
        "controlling_field" : "enable_overrides",
        "controlling_field_path" : "module_overrides.background_settings.select_background_color_type",
        "controlling_value_regex" : "custom",
        "property" : null,
        "operator" : "EQUAL",
        "access" : null
      },
      "type" : "color",
      "display_width" : null,
      "default" : {
        "color" : null,
        "opacity" : null
      }
    }, {
      "id" : "878364f4-31ac-6917-e76f-65307d7d36e5",
      "name" : "background_image",
      "label" : "Background Image",
      "help_text" : "If a module has formal settings for a background image they will take priority over this value.",
      "required" : false,
      "locked" : false,
      "visibility" : {
        "controlling_field" : "enable_overrides",
        "controlling_field_path" : "module_overrides.background_settings.background_type",
        "controlling_value_regex" : "image",
        "property" : null,
        "operator" : "EQUAL",
        "access" : null
      },
      "responsive" : true,
      "resizable" : false,
      "show_loading" : false,
      "type" : "image",
      "display_width" : null,
      "default" : {
        "size_type" : "auto",
        "src" : "",
        "alt" : null,
        "loading" : "disabled"
      }
    } ],
    "tab" : "CONTENT",
    "expanded" : false,
    "group_occurrence_meta" : null,
    "type" : "group",
    "display_width" : null,
    "default" : {
      "background_type" : "color",
      "select_background_color_type" : "brown",
      "background_color" : {
        "color" : null,
        "opacity" : null
      },
      "background_image" : {
        "size_type" : "auto",
        "src" : "",
        "alt" : null,
        "loading" : "disabled"
      }
    }
  }, {
    "id" : "b8ff09cf-3e4e-fe6d-88bc-95be48ab2e1e",
    "name" : "reverse_text",
    "label" : "Reverse Text",
    "required" : false,
    "locked" : false,
    "visibility" : {
      "controlling_field" : null,
      "controlling_field_path" : "module_overrides.enable_overrides",
      "controlling_value_regex" : "true",
      "property" : null,
      "operator" : "EQUAL",
      "access" : null
    },
    "display" : "checkbox",
    "type" : "boolean",
    "display_width" : null,
    "default" : true
  } ],
  "tab" : "CONTENT",
  "expanded" : false,
  "group_occurrence_meta" : null,
  "type" : "group",
  "display_width" : null,
  "default" : {
    "enable_overrides" : true,
    "top_margin" : "top-margin-default",
    "custom_top_margin" : 100,
    "custom_top_margin_mobile" : 50,
    "bottom_margin" : "bottom-margin-default",
    "custom_bottom_margin" : 100,
    "custom_bottom_margin_mobile" : 50,
    "top_padding" : "top-padding-default",
    "custom_top_padding" : 100,
    "custom_top_padding_mobile" : 50,
    "bottom_padding" : "bottom-padding-default",
    "custom_bottom_padding" : 100,
    "custom_bottom_padding_mobile" : 50,
    "background_settings" : {
      "background_type" : "color",
      "select_background_color_type" : "brown",
      "background_color" : {
        "color" : null,
        "opacity" : null
      },
      "background_image" : {
        "size_type" : "auto",
        "src" : "",
        "alt" : null,
        "loading" : "disabled"
      }
    },
    "reverse_text" : true
  }
} ]